<?xml version="1.0" encoding="utf-8" ?><dwsync><file name="controller.php" server="Macintosh HD/Applications/XAMPP/xamppfiles/htdocs/" local="3504431438" remote="1137886133278040398" Dst="-1" /><file name="model.php" server="Macintosh HD/Applications/XAMPP/xamppfiles/htdocs/" local="3504431438" remote="1137886133278040398" Dst="-1" /><file name="pip.php" server="Macintosh HD/Applications/XAMPP/xamppfiles/htdocs/" local="3504431438" remote="1137886133278040398" Dst="-1" /><file name="view.php" server="Macintosh HD/Applications/XAMPP/xamppfiles/htdocs/" local="3504431438" remote="1137886133278040398" Dst="-1" /><file name="view.php" server="109.73.234.188/pkd/" local="3517588080" remote="7812555376" Dst="-1" /><file name="controller.php" server="109.73.234.188/pkd/" local="3517588080" remote="7812555376" Dst="-1" /><file name="model.php" server="109.73.234.188/pkd/" local="3517588080" remote="7812555376" Dst="-1" /><file name="pip.php" server="109.73.234.188/pkd/" local="3517588080" remote="7812555376" Dst="-1" /><file name="pip.php" server="178.62.65.198/../../var/www/prachikotharidesigns/public_html/" local="3504431438" remote="-4611744340560266370" Dst="-1" /><file name="controller.php" server="178.62.65.198/../../var/www/prachikotharidesigns/public_html/" local="3504431438" remote="3724292847419833212" Dst="-1" /><file name="model.php" server="178.62.65.198/../../var/www/prachikotharidesigns/public_html/" local="3504431438" remote="-4611744340560266371" Dst="-1" /><file name="view.php" server="178.62.65.198/../../var/www/prachikotharidesigns/public_html/" local="3504431438" remote="-4611744340560266369" Dst="-1" /></dwsync>